cubedash/__init__.py
cubedash/_api.py
cubedash/_audit.py
cubedash/_dataset.py
cubedash/_filters.py
cubedash/_model.py
cubedash/_monitoring.py
cubedash/_pages.py
cubedash/_platform.py
cubedash/_product.py
cubedash/_stac.py
cubedash/_stac_legacy.py
cubedash/_utils.py
cubedash/_version.py
cubedash/generate.py
cubedash/gunicorn_config.py
cubedash/logs.py
cubedash/run.py
cubedash/warmup.py
cubedash/data/WRS2_ascending/WRS2_acsending.cpg
cubedash/data/WRS2_ascending/WRS2_acsending.csv
cubedash/data/WRS2_ascending/WRS2_acsending.dbf
cubedash/data/WRS2_ascending/WRS2_acsending.prj
cubedash/data/WRS2_ascending/WRS2_acsending.sbn
cubedash/data/WRS2_ascending/WRS2_acsending.sbx
cubedash/data/WRS2_ascending/WRS2_acsending.shp
cubedash/data/WRS2_ascending/WRS2_acsending.shx
cubedash/data/WRS2_ascending/WRS2_acsending.xml
cubedash/data/WRS2_descending/WRS2_descending.cpg
cubedash/data/WRS2_descending/WRS2_descending.dbf
cubedash/data/WRS2_descending/WRS2_descending.prj
cubedash/data/WRS2_descending/WRS2_descending.sbn
cubedash/data/WRS2_descending/WRS2_descending.sbx
cubedash/data/WRS2_descending/WRS2_descending.shp
cubedash/data/WRS2_descending/WRS2_descending.shx
cubedash/data/WRS2_descending/WRS2_descending.xml
cubedash/index/__init__.py
cubedash/index/api.py
cubedash/index/postgis/__init__.py
cubedash/index/postgis/_api.py
cubedash/index/postgis/_schema.py
cubedash/index/postgres/__init__.py
cubedash/index/postgres/_api.py
cubedash/index/postgres/_schema.py
cubedash/static/base.css
cubedash/static/base.css.map
cubedash/static/base.sass
cubedash/static/dea-icon.svg
cubedash/static/dea-logo-inline.png
cubedash/static/dea.svg
cubedash/static/jquery-3.3.1.min.js
cubedash/static/normalise.css
cubedash/static/overview.js
cubedash/static/overview.js.map
cubedash/static/overview.ts
cubedash/static/tsconfig.json
cubedash/static/fontawesome-free-6.2.0-web/css/fontawesome.min.css
cubedash/static/fontawesome-free-6.2.0-web/css/regular.min.css
datacube_explorer-3.1.2.dist-info/licenses/LICENSE
datacube_explorer-3.1.2.dist-info/METADATA
datacube_explorer-3.1.2.dist-info/WHEEL
datacube_explorer-3.1.2.dist-info/entry_points.txt
datacube_explorer-3.1.2.dist-info/top_level.txt
datacube_explorer-3.1.2.dist-info/RECORD
