Metadata-Version: 2.4
Name: datacube-explorer
Version: 3.1.2
Summary: Web-based exploration of Open Data Cube collections
Author-email: Geoscience Australia <earth.observation@ga.gov.au>
License-Expression: Apache-2.0
Project-URL: Homepage, https://github.com/opendatacube/datacube-explorer
Project-URL: Bug Reports, https://github.com/opendatacube/datacube-explorer/issues
Project-URL: Source, https://github.com/opendatacube/datacube-explorer
Classifier: Operating System :: OS Independent
Classifier: Programming Language :: Python :: 3
Classifier: Programming Language :: Python :: 3.10
Classifier: Programming Language :: Python :: 3.11
Classifier: Programming Language :: Python :: 3.12
Classifier: Programming Language :: Python :: 3.13
Requires-Python: >=3.10
License-File: LICENSE
Requires-Dist: Flask-Caching
Requires-Dist: cachetools
Requires-Dist: click<8.2.0
Requires-Dist: datacube[postgres]<1.10.0,>=1.9.10
Requires-Dist: eodatasets3>=1.9
Requires-Dist: fiona>=1.10.0
Requires-Dist: flask
Requires-Dist: flask-cors
Requires-Dist: flask-themer>=1.4.3
Requires-Dist: geoalchemy2>=0.8
Requires-Dist: geographiclib
Requires-Dist: jinja2
Requires-Dist: markupsafe
Requires-Dist: odc-geo
Requires-Dist: orjson>=3
Requires-Dist: psycopg[c]
Requires-Dist: pygeofilter>=0.2.2
Requires-Dist: pyorbital
Requires-Dist: pyproj
Requires-Dist: pystac
Requires-Dist: sentry-sdk[flask]
Requires-Dist: shapely
Requires-Dist: simplekml
Requires-Dist: sqlalchemy>=1.4
Requires-Dist: structlog>=20.2.0
Provides-Extra: deployment
Requires-Dist: bottleneck; extra == "deployment"
Requires-Dist: ciso8601; extra == "deployment"
Requires-Dist: gevent; extra == "deployment"
Requires-Dist: gunicorn>=22.0.0; extra == "deployment"
Requires-Dist: setproctitle; extra == "deployment"
Requires-Dist: blinker; extra == "deployment"
Requires-Dist: prometheus-flask-exporter; extra == "deployment"
Provides-Extra: test
Requires-Dist: datacube-explorer[deployment]; extra == "test"
Requires-Dist: blinker; extra == "test"
Requires-Dist: boltons; extra == "test"
Requires-Dist: deepdiff; extra == "test"
Requires-Dist: docker; extra == "test"
Requires-Dist: docutils; extra == "test"
Requires-Dist: jsonschema>=4.18; extra == "test"
Requires-Dist: lxml_html_clean; extra == "test"
Requires-Dist: mypy; extra == "test"
Requires-Dist: pre-commit; extra == "test"
Requires-Dist: prometheus-flask-exporter; extra == "test"
Requires-Dist: pytest; extra == "test"
Requires-Dist: pytest-benchmark; extra == "test"
Requires-Dist: pytest-cov; extra == "test"
Requires-Dist: ruff; extra == "test"
Requires-Dist: selectolax; extra == "test"
Requires-Dist: types-cachetools; extra == "test"
Requires-Dist: types-docker; extra == "test"
Requires-Dist: types-pyyaml; extra == "test"
Dynamic: license-file
